README.md
pyproject.toml
setup.py
redis_key_tagging/__init__.py
redis_key_tagging/client.py
redis_key_tagging.egg-info/PKG-INFO
redis_key_tagging.egg-info/SOURCES.txt
redis_key_tagging.egg-info/dependency_links.txt
redis_key_tagging.egg-info/requires.txt
redis_key_tagging.egg-info/top_level.txt
redis_key_tagging/tests/__init__.py
redis_key_tagging/tests/test_client.py