Metadata-Version: 2.1
Name: redis-key-tagging
Version: 0.0.5
Summary: A Redis client with key tagging and invalidation by tag features.
Home-page: https://github.com/erudit/redis_key_tagging
Author: Consortium Érudit
Author-email: tech@erudit.org
License: UNKNOWN
Platform: UNKNOWN
Classifier: Programming Language :: Python :: 3
Classifier: License :: OSI Approved :: GNU General Public License v3 (GPLv3)
Classifier: Operating System :: OS Independent
Requires-Python: >=3.6
